CYuyanJinjie/README.md
CYuyanJinjie/__init__.py
CYuyanJinjie/__main__.py
CYuyanJinjie/file.epub
CYuyanJinjie/index.html
CYuyanJinjie/css/__init__.py
CYuyanJinjie/css/annotations.css
CYuyanJinjie/css/main.css
CYuyanJinjie/css/normalize.css
CYuyanJinjie/css/popup.css
CYuyanJinjie/font/__init__.py
CYuyanJinjie/font/fontello.eot
CYuyanJinjie/font/fontello.svg
CYuyanJinjie/font/fontello.ttf
CYuyanJinjie/font/fontello.woff
CYuyanJinjie/img/__init__.py
CYuyanJinjie/img/annotator-glyph-sprite.png
CYuyanJinjie/img/annotator-icon-sprite.png
CYuyanJinjie/img/apple-touch-icon.png
CYuyanJinjie/img/cancelfullscreen.png
CYuyanJinjie/img/close.png
CYuyanJinjie/img/fullscreen.png
CYuyanJinjie/img/loader.gif
CYuyanJinjie/img/menu-icon.png
CYuyanJinjie/img/save.png
CYuyanJinjie/img/saved.png
CYuyanJinjie/img/settings-s.png
CYuyanJinjie/img/settings.png
CYuyanJinjie/img/star.png
CYuyanJinjie/js/__init__.py
CYuyanJinjie/js/epub.js
CYuyanJinjie/js/epub.min.js
CYuyanJinjie/js/epub.min.map
CYuyanJinjie/js/hooks.min.js
CYuyanJinjie/js/hooks.min.map
CYuyanJinjie/js/reader.js
CYuyanJinjie/js/reader.js.map
CYuyanJinjie/js/reader.min.js
CYuyanJinjie/js/reader.min.map
CYuyanJinjie/js/hooks/__init__.py
CYuyanJinjie/js/hooks/extensions/__init__.py
CYuyanJinjie/js/hooks/extensions/highlight.js
CYuyanJinjie/js/libs/__init__.py
CYuyanJinjie/js/libs/jquery.min.js
CYuyanJinjie/js/libs/localforage.min.js
CYuyanJinjie/js/libs/screenfull.js
CYuyanJinjie/js/libs/screenfull.min.js
CYuyanJinjie/js/libs/zip.min.js
CYuyanJinjie/js/plugins/__init__.py
CYuyanJinjie/js/plugins/hypothesis.js
CYuyanJinjie/js/plugins/search.js
c_yuyan_jinjie-2024.3.4.0.dist-info/METADATA
c_yuyan_jinjie-2024.3.4.0.dist-info/WHEEL
c_yuyan_jinjie-2024.3.4.0.dist-info/entry_points.txt
c_yuyan_jinjie-2024.3.4.0.dist-info/top_level.txt
c_yuyan_jinjie-2024.3.4.0.dist-info/RECORD
